explain_ai_generated_text/Random_Forest_model.joblib
explain_ai_generated_text/XGB_model.joblib
explain_ai_generated_text/__init__.py
explain_ai_generated_text/coling.csv
explain_ai_generated_text/core.py
explain_ai_generated_text/test.py
explain_ai_generated_text/utils.py
explain_ai_generated_text-0.1.1.1.7.dist-info/METADATA
explain_ai_generated_text-0.1.1.1.7.dist-info/WHEEL
explain_ai_generated_text-0.1.1.1.7.dist-info/top_level.txt
explain_ai_generated_text-0.1.1.1.7.dist-info/RECORD
