Metadata-Version: 2.4
Name: explain_ai_generated_text
Version: 0.1.1.1.7
Summary: A library to explain whether text is AI-generated or human-written using SHAP
Author-email: Shushanta Pudasaini <d23129142@mytublin.ie>
Keywords: AI,text-classification,explainability,SHAP
Classifier: Development Status :: 3 - Alpha
Classifier: Intended Audience :: Developers
Classifier: License :: OSI Approved :: MIT License
Classifier: Programming Language :: Python :: 3
Classifier: Programming Language :: Python :: 3.8
Classifier: Programming Language :: Python :: 3.9
Classifier: Programming Language :: Python :: 3.10
Classifier: Programming Language :: Python :: 3.11
Requires-Python: >=3.8
Requires-Dist: joblib
Requires-Dist: shap
Requires-Dist: xgboost
Requires-Dist: spacy
Requires-Dist: language-tool-python
Requires-Dist: textblob
Requires-Dist: pandas
Requires-Dist: numpy
Requires-Dist: scikit-learn
Requires-Dist: nltk
Requires-Dist: textstat
Requires-Dist: matplotlib
Requires-Dist: scipy
Provides-Extra: dev
Requires-Dist: pytest; extra == "dev"
Requires-Dist: black; extra == "dev"
Requires-Dist: flake8; extra == "dev"
